LICENSE
README.md
setup.py
pyucallerapi/__init__.py
pyucallerapi/api.py
pyucallerapi/decorators.py
pyucallerapi/exception.py
pyucallerapi/models.py
pyucallerapi.egg-info/PKG-INFO
pyucallerapi.egg-info/SOURCES.txt
pyucallerapi.egg-info/dependency_links.txt
pyucallerapi.egg-info/not-zip-safe
pyucallerapi.egg-info/requires.txt
pyucallerapi.egg-info/top_level.txt