Metadata-Version: 2.4
Name: pyucallerapi
Version: 0.1.0
Summary: Python service for convenient work with uCaller API
Author: kebrick
Author-email: ruban.kebr@gmail.com
License: MIT
Project-URL: Source, https://github.com/kebrick/pyucallerapi
Project-URL: Tracker, https://github.com/kebrick/pyucallerapi/issues
Classifier: Programming Language :: Python :: 3
Classifier: Programming Language :: Python :: 3.10
Classifier: Programming Language :: Python :: 3.11
Classifier: Programming Language :: Python :: 3.12
Classifier: Programming Language :: Python :: 3.13
Classifier: Operating System :: OS Independent
Requires-Python: >=3.10
License-File: LICENSE
Requires-Dist: requests
Dynamic: author
Dynamic: author-email
Dynamic: classifier
Dynamic: description
Dynamic: description-content-type
Dynamic: license
Dynamic: license-file
Dynamic: project-url
Dynamic: requires-dist
Dynamic: requires-python
Dynamic: summary
